hyperion_obf/__init__.py
Hyperion_obf-1.0.0.dist-info/LICENSE
Hyperion_obf-1.0.0.dist-info/METADATA
Hyperion_obf-1.0.0.dist-info/WHEEL
Hyperion_obf-1.0.0.dist-info/top_level.txt
Hyperion_obf-1.0.0.dist-info/RECORD
