Metadata-Version: 2.1
Name: Hyperion-obf
Version: 1.0.0
Summary: Python obfuscator that use hyperion
Home-page: https://github.com/LeRatGondin/Hyperion_obf
Author: LeRatGondin
Author-email: leratgondin1@gmail.com
License: EPL 2.0
Project-URL: Bug Tracker, https://github.com/LeRatGondin/Hyperion_obf/issues
Classifier: Programming Language :: Python :: 3
Classifier: License :: OSI Approved :: Eclipse Public License 2.0 (EPL-2.0)
Classifier: Operating System :: OS Independent
Requires-Python: >=3.6
License-File: LICENSE
